colour_of_molecule/__init__.py
colour_of_molecule/analysis/__init__.py
colour_of_molecule/analysis/common_tools.py
colour_of_molecule/analysis/spectrum.py
colour_of_molecule/classes/__init__.py
colour_of_molecule/classes/classes.py
colour_of_molecule/input/__init__.py
colour_of_molecule/input/gaussian.py
colour_of_molecule/input/mndo.py
colour_of_molecule/input/molpro.py
colour_of_molecule/input/orca.py
colour_of_molecule/plotting/__init__.py
colour_of_molecule/plotting/plot_spectra.py
colour_of_molecule/templates/__init__.py
colour_of_molecule/templates/analyze_multiple_files.py
colour_of_molecule/templates/find_colour.py
colour_of_molecule/templates/plot_spectrum.py
colour_of_molecule/templates/testing_pyth.py
colour_of_molecule-0.0.3.dev2.dist-info/LICENSE
colour_of_molecule-0.0.3.dev2.dist-info/METADATA
colour_of_molecule-0.0.3.dev2.dist-info/WHEEL
colour_of_molecule-0.0.3.dev2.dist-info/top_level.txt
colour_of_molecule-0.0.3.dev2.dist-info/RECORD
