Metadata-Version: 2.1
Name: colour-of-molecule
Version: 0.0.3.dev2
Summary: Tools for colour related analysis of various QCh software output files.
Home-page: https://github.com/MichalPt/colour_of_molecule
Author: Michal Ptacek
Author-email: ptacekmichal@outlook.com
License: MIT
Platform: UNKNOWN
Classifier: Programming Language :: Python :: 3
Classifier: License :: OSI Approved :: MIT License
Classifier: Operating System :: OS Independent
Requires-Python: >=3.6
License-File: LICENSE
Requires-Dist: colour-science
Requires-Dist: numpy
Requires-Dist: matplotlib
Requires-Dist: InquirerPy
